{
    "17180": "Все на хоккей 💣",
    "17157": "Уважаемые знатоки!\nСкоро сессия.\nМожет кому-то стоит сразу в академ???",
    "17155": "🔥🔥🔥",
    "17153": "",
    "17152": "Обратите внимание на объявление об изменении мест проведения занятий по физкультуре на следующей неделе!",
    "17150": "К заместителю декана Ю.В. Берчуну приглашаются следующие студенты:\n\nРК4-21 - Аксенов, Горбатенко, Трипкош\nРК5-21Б - Серков, Лазаев, Кочанов\nРК5-22Б - Тарасенко, Казаков\nРК5-23Б - Сырцев, Люхтер\nРК6-21Б - Байков\nРК6-22Б - Фролкин\nРК6-23Б - Ковалик, Астахов, Коджаков\nРК6-24Б - Личко, Куликов, Костиков\nРК6-25Б - Мильчевский, Курбатов, Палагнюк\nРК6-26Б - Зуюнов, Пахомов, Атрошко\nРК6-27Б - Степанов, Полосков, Никифоров\nРК6-28Б - Венедиктов\nРК9-21Б - Скулков, Чичигин, Гурьев\nРК9-22Б - Садыков\nРК9-23Б - Смирнов, Иваненко, Зайцев, Геворкян, Просников, Гилев\nРК9-24Б - Штепа, Магомедов, Васильев\nРК5-41Б - Немойкин, Чуприн, Малахов\nРК9-43Б - Лиманов\nРК4-89 - Ульянов\nРК5-83Б - Ивченко\nРК9-83Б - Юлдашев\nРК6-21М - Егиазарян\nРК9-21М - Москаленко",
    "17149": "Обращаю Ваше внимание ПОВТОРНО!!! \nСтудентам первого курса подойти в деканат в 303ю (с 9-30 до 15.30) для заполнения учебных карточек:\nРК4-21 Михайлов А.В.\nРК6-25Б Панарин М.А.\nРК6-26Б Менешов М.Б.\nРК6-26Б Назриллаев А.У.",
    "17146": ""
}